observify/__init__.py
observify/batching.py
observify/middleware.py
observify/types.py
observify/py.typed
observify-1.0.2.dist-info/METADATA
observify-1.0.2.dist-info/WHEEL
observify-1.0.2.dist-info/RECORD
