Metadata-Version: 2.4
Name: observify
Version: 1.0.2
Summary: SDK de métricas HTTP para FastAPI e Django com batch e retries
Author-email: Guilherme Gradaschi <guilhermegradas@gmail.com>
License: MIT
Keywords: asgi,django,fastapi,metrics,middleware,observability
Classifier: Framework :: Django
Classifier: Framework :: FastAPI
Classifier: License :: OSI Approved :: MIT License
Classifier: Programming Language :: Python :: 3
Classifier: Topic :: System :: Monitoring
Classifier: Typing :: Typed
Requires-Python: >=3.8
Requires-Dist: requests>=2.28
